{"symbol":"UBER","spot":65.98,"asof":"2026-07-24 19:46:23","today":"2026-07-24","generated":"2026-07-24T19:47:24.549Z","floor":200,"strikePct":0.12,"autoExpiries":["2026-07-24","2026-07-31","2026-08-07","2026-08-14","2026-08-21"],"contracts":[{"e":"2026-07-24","t":"P","k":61,"oi":206,"g":0.007,"v":30},{"e":"2026-07-24","t":"P","k":63,"oi":248,"g":0.0304,"v":219},{"e":"2026-07-24","t":"P","k":64,"oi":425,"g":0.1021,"v":138},{"e":"2026-07-24","t":"P","k":65,"oi":905,"g":0.2269,"v":1375},{"e":"2026-07-24","t":"P","k":66,"oi":658,"g":0.3992,"v":7235},{"e":"2026-07-24","t":"P","k":67,"oi":1243,"g":0.2363,"v":1833},{"e":"2026-07-24","t":"C","k":68,"oi":202,"g":0.0379,"v":1650},{"e":"2026-07-24","t":"P","k":68,"oi":2200,"g":0.0379,"v":2060},{"e":"2026-07-24","t":"C","k":69,"oi":934,"g":0.0199,"v":1301},{"e":"2026-07-24","t":"P","k":69,"oi":2596,"g":0.0199,"v":5703},{"e":"2026-07-24","t":"C","k":70,"oi":1812,"g":0.0127,"v":3204},{"e":"2026-07-24","t":"P","k":70,"oi":5372,"g":0.0127,"v":1089},{"e":"2026-07-24","t":"C","k":71,"oi":3069,"g":0.0089,"v":2003},{"e":"2026-07-24","t":"P","k":71,"oi":2512,"g":0.0089,"v":581},{"e":"2026-07-24","t":"C","k":72,"oi":3802,"g":0.0066,"v":570},{"e":"2026-07-24","t":"P","k":72,"oi":1587,"g":0.0066,"v":153},{"e":"2026-07-24","t":"C","k":73,"oi":5697,"g":0.0052,"v":119},{"e":"2026-07-24","t":"P","k":73,"oi":458,"g":0.0052,"v":56},{"e":"2026-07-24","t":"C","k":74,"oi":4439,"g":0.0042,"v":40},{"e":"2026-07-24","t":"C","k":75,"oi":5167,"g":0.0034,"v":825},{"e":"2026-07-31","t":"P","k":61,"oi":3096,"g":0.0421,"v":194},{"e":"2026-07-31","t":"P","k":62,"oi":11878,"g":0.0566,"v":5087},{"e":"2026-07-31","t":"P","k":64,"oi":248,"g":0.0856,"v":221},{"e":"2026-07-31","t":"P","k":65,"oi":544,"g":0.0948,"v":1475},{"e":"2026-07-31","t":"P","k":66,"oi":1647,"g":0.0987,"v":934},{"e":"2026-07-31","t":"P","k":67,"oi":6296,"g":0.0973,"v":800},{"e":"2026-07-31","t":"P","k":68,"oi":1740,"g":0.0909,"v":1092},{"e":"2026-07-31","t":"C","k":69,"oi":427,"g":0.0792,"v":1438},{"e":"2026-07-31","t":"P","k":69,"oi":3556,"g":0.08,"v":4040},{"e":"2026-07-31","t":"C","k":70,"oi":1349,"g":0.065,"v":1683},{"e":"2026-07-31","t":"P","k":70,"oi":3999,"g":0.0656,"v":604},{"e":"2026-07-31","t":"C","k":71,"oi":2001,"g":0.0502,"v":1597},{"e":"2026-07-31","t":"P","k":71,"oi":790,"g":0.0505,"v":58},{"e":"2026-07-31","t":"C","k":72,"oi":907,"g":0.0373,"v":1195},{"e":"2026-07-31","t":"P","k":72,"oi":840,"g":0.0372,"v":98},{"e":"2026-07-31","t":"C","k":73,"oi":2499,"g":0.0274,"v":882},{"e":"2026-07-31","t":"P","k":73,"oi":529,"g":0.0269,"v":30},{"e":"2026-07-31","t":"C","k":74,"oi":1155,"g":0.0202,"v":1155},{"e":"2026-07-31","t":"C","k":75,"oi":4679,"g":0.0152,"v":1478},{"e":"2026-07-31","t":"P","k":75,"oi":364,"g":0.0142,"v":408},{"e":"2026-08-07","t":"P","k":63,"oi":578,"g":0.0457,"v":14},{"e":"2026-08-07","t":"P","k":65,"oi":1193,"g":0.05,"v":177},{"e":"2026-08-07","t":"P","k":66,"oi":436,"g":0.0511,"v":921},{"e":"2026-08-07","t":"P","k":67,"oi":459,"g":0.0514,"v":365},{"e":"2026-08-07","t":"P","k":68,"oi":539,"g":0.051,"v":279},{"e":"2026-08-07","t":"P","k":69,"oi":319,"g":0.0498,"v":58},{"e":"2026-08-07","t":"C","k":70,"oi":200,"g":0.0475,"v":3514},{"e":"2026-08-07","t":"P","k":70,"oi":1352,"g":0.048,"v":257},{"e":"2026-08-07","t":"C","k":71,"oi":248,"g":0.0449,"v":231},{"e":"2026-08-07","t":"C","k":72,"oi":483,"g":0.0418,"v":1380},{"e":"2026-08-07","t":"P","k":72,"oi":774,"g":0.0423,"v":17},{"e":"2026-08-07","t":"C","k":73,"oi":243,"g":0.0382,"v":239},{"e":"2026-08-07","t":"P","k":73,"oi":266,"g":0.0388,"v":7},{"e":"2026-08-07","t":"C","k":74,"oi":336,"g":0.0344,"v":101},{"e":"2026-08-07","t":"C","k":75,"oi":4742,"g":0.0306,"v":2202},{"e":"2026-08-14","t":"P","k":60,"oi":8051,"g":0.0336,"v":22},{"e":"2026-08-14","t":"P","k":65,"oi":237,"g":0.0458,"v":91},{"e":"2026-08-14","t":"C","k":75,"oi":315,"g":0.0311,"v":48},{"e":"2026-08-21","t":"P","k":60,"oi":17296,"g":0.0323,"v":511},{"e":"2026-08-21","t":"P","k":62,"oi":691,"g":0.0377,"v":65},{"e":"2026-08-21","t":"P","k":62.5,"oi":3032,"g":0.0389,"v":63},{"e":"2026-08-21","t":"P","k":64,"oi":380,"g":0.0418,"v":38},{"e":"2026-08-21","t":"C","k":65,"oi":506,"g":0.0428,"v":18},{"e":"2026-08-21","t":"P","k":65,"oi":12023,"g":0.0432,"v":432},{"e":"2026-08-21","t":"P","k":67,"oi":465,"g":0.0445,"v":1290},{"e":"2026-08-21","t":"C","k":67.5,"oi":271,"g":0.044,"v":63},{"e":"2026-08-21","t":"P","k":67.5,"oi":4829,"g":0.0445,"v":298},{"e":"2026-08-21","t":"P","k":68,"oi":253,"g":0.0444,"v":126},{"e":"2026-08-21","t":"C","k":70,"oi":2450,"g":0.042,"v":2806},{"e":"2026-08-21","t":"P","k":70,"oi":8575,"g":0.0427,"v":134},{"e":"2026-08-21","t":"C","k":72,"oi":221,"g":0.0384,"v":231},{"e":"2026-08-21","t":"C","k":72.5,"oi":2440,"g":0.0373,"v":168},{"e":"2026-08-21","t":"P","k":72.5,"oi":4086,"g":0.0382,"v":52},{"e":"2026-08-21","t":"C","k":75,"oi":8656,"g":0.0311,"v":486},{"e":"2026-08-21","t":"P","k":75,"oi":3268,"g":0.0321,"v":51},{"e":"2026-08-28","t":"P","k":70,"oi":2185,"g":0.0397,"v":28},{"e":"2026-09-18","t":"C","k":60,"oi":777,"g":0.0274,"v":38},{"e":"2026-09-18","t":"P","k":60,"oi":9720,"g":0.0277,"v":496},{"e":"2026-09-18","t":"C","k":62.5,"oi":639,"g":0.0314,"v":1},{"e":"2026-09-18","t":"P","k":62.5,"oi":7417,"g":0.0319,"v":203},{"e":"2026-09-18","t":"C","k":65,"oi":725,"g":0.0342,"v":47},{"e":"2026-09-18","t":"P","k":65,"oi":14688,"g":0.0348,"v":156},{"e":"2026-09-18","t":"C","k":67.5,"oi":264,"g":0.0353,"v":352},{"e":"2026-09-18","t":"P","k":67.5,"oi":4646,"g":0.0361,"v":269},{"e":"2026-09-18","t":"C","k":70,"oi":2710,"g":0.0346,"v":193},{"e":"2026-09-18","t":"P","k":70,"oi":14154,"g":0.0356,"v":416},{"e":"2026-09-18","t":"C","k":72.5,"oi":2509,"g":0.0324,"v":120},{"e":"2026-09-18","t":"P","k":72.5,"oi":3488,"g":0.0336,"v":41},{"e":"2026-09-18","t":"C","k":75,"oi":5796,"g":0.0292,"v":1138},{"e":"2026-09-18","t":"P","k":75,"oi":6822,"g":0.0305,"v":12},{"e":"2026-10-16","t":"P","k":60,"oi":450,"g":0.0241,"v":623},{"e":"2026-10-16","t":"P","k":65,"oi":1224,"g":0.0289,"v":27},{"e":"2026-10-16","t":"P","k":67.5,"oi":953,"g":0.03,"v":20},{"e":"2026-10-16","t":"C","k":70,"oi":295,"g":0.0291,"v":52},{"e":"2026-10-16","t":"P","k":70,"oi":1117,"g":0.0302,"v":3},{"e":"2026-10-16","t":"C","k":72.5,"oi":260,"g":0.0281,"v":98},{"e":"2026-10-16","t":"P","k":72.5,"oi":215,"g":0.0294,"v":1},{"e":"2026-10-16","t":"C","k":75,"oi":305,"g":0.0264,"v":189},{"e":"2026-10-16","t":"P","k":75,"oi":689,"g":0.0279,"v":13},{"e":"2026-11-20","t":"C","k":60,"oi":358,"g":0.0203,"v":8},{"e":"2026-11-20","t":"P","k":60,"oi":5116,"g":0.0208,"v":566},{"e":"2026-11-20","t":"P","k":62.5,"oi":2442,"g":0.0228,"v":104},{"e":"2026-11-20","t":"C","k":65,"oi":343,"g":0.0235,"v":13},{"e":"2026-11-20","t":"P","k":65,"oi":5737,"g":0.0243,"v":56},{"e":"2026-11-20","t":"P","k":67.5,"oi":1777,"g":0.0252,"v":116},{"e":"2026-11-20","t":"C","k":70,"oi":484,"g":0.0245,"v":44},{"e":"2026-11-20","t":"P","k":70,"oi":5456,"g":0.0256,"v":96},{"e":"2026-11-20","t":"C","k":72.5,"oi":716,"g":0.0241,"v":5},{"e":"2026-11-20","t":"P","k":72.5,"oi":1549,"g":0.0254,"v":4},{"e":"2026-11-20","t":"C","k":75,"oi":1357,"g":0.0233,"v":29},{"e":"2026-11-20","t":"P","k":75,"oi":616,"g":0.0248,"v":15},{"e":"2026-12-18","t":"P","k":57.5,"oi":4913,"g":0.0174,"v":3},{"e":"2026-12-18","t":"C","k":60,"oi":948,"g":0.0188,"v":31},{"e":"2026-12-18","t":"P","k":60,"oi":8083,"g":0.0194,"v":79},{"e":"2026-12-18","t":"P","k":62.5,"oi":1747,"g":0.0211,"v":24},{"e":"2026-12-18","t":"C","k":65,"oi":564,"g":0.0215,"v":20},{"e":"2026-12-18","t":"P","k":65,"oi":7145,"g":0.0224,"v":32},{"e":"2026-12-18","t":"P","k":67.5,"oi":2338,"g":0.0233,"v":75},{"e":"2026-12-18","t":"C","k":70,"oi":1142,"g":0.0226,"v":30},{"e":"2026-12-18","t":"P","k":70,"oi":4267,"g":0.0238,"v":36},{"e":"2026-12-18","t":"C","k":72.5,"oi":1582,"g":0.0224,"v":445},{"e":"2026-12-18","t":"P","k":72.5,"oi":1909,"g":0.0238,"v":68},{"e":"2026-12-18","t":"C","k":75,"oi":4328,"g":0.0219,"v":37},{"e":"2026-12-18","t":"P","k":75,"oi":2150,"g":0.0235,"v":8},{"e":"2027-01-15","t":"P","k":57.5,"oi":3363,"g":0.0165,"v":17},{"e":"2027-01-15","t":"C","k":60,"oi":1981,"g":0.0176,"v":20},{"e":"2027-01-15","t":"P","k":60,"oi":12595,"g":0.0182,"v":467},{"e":"2027-01-15","t":"C","k":62.5,"oi":386,"g":0.0189,"v":32},{"e":"2027-01-15","t":"P","k":62.5,"oi":6929,"g":0.0197,"v":52},{"e":"2027-01-15","t":"C","k":65,"oi":2119,"g":0.02,"v":25},{"e":"2027-01-15","t":"P","k":65,"oi":10805,"g":0.0209,"v":845},{"e":"2027-01-15","t":"C","k":67.5,"oi":604,"g":0.0207,"v":13},{"e":"2027-01-15","t":"P","k":67.5,"oi":4469,"g":0.0218,"v":37},{"e":"2027-01-15","t":"C","k":70,"oi":3472,"g":0.021,"v":123},{"e":"2027-01-15","t":"P","k":70,"oi":9595,"g":0.0223,"v":268},{"e":"2027-01-15","t":"C","k":72.5,"oi":1391,"g":0.021,"v":93},{"e":"2027-01-15","t":"P","k":72.5,"oi":5631,"g":0.0225,"v":45},{"e":"2027-01-15","t":"C","k":75,"oi":7265,"g":0.0207,"v":561},{"e":"2027-01-15","t":"P","k":75,"oi":12453,"g":0.0224,"v":21},{"e":"2027-03-19","t":"C","k":60,"oi":854,"g":0.015,"v":12},{"e":"2027-03-19","t":"P","k":60,"oi":4454,"g":0.0157,"v":2},{"e":"2027-03-19","t":"P","k":62.5,"oi":1207,"g":0.0168,"v":1},{"e":"2027-03-19","t":"C","k":65,"oi":336,"g":0.0167,"v":7},{"e":"2027-03-19","t":"P","k":65,"oi":572,"g":0.0178,"v":2},{"e":"2027-03-19","t":"P","k":67.5,"oi":920,"g":0.0185,"v":0},{"e":"2027-03-19","t":"C","k":70,"oi":524,"g":0.0177,"v":64},{"e":"2027-03-19","t":"P","k":70,"oi":1696,"g":0.0191,"v":0},{"e":"2027-03-19","t":"C","k":72.5,"oi":693,"g":0.0178,"v":3},{"e":"2027-03-19","t":"P","k":72.5,"oi":867,"g":0.0194,"v":0},{"e":"2027-03-19","t":"C","k":75,"oi":1052,"g":0.0178,"v":59},{"e":"2027-03-19","t":"P","k":75,"oi":320,"g":0.0196,"v":0},{"e":"2027-06-17","t":"C","k":60,"oi":390,"g":0.0126,"v":0},{"e":"2027-06-17","t":"P","k":60,"oi":9995,"g":0.0134,"v":1},{"e":"2027-06-17","t":"P","k":62.5,"oi":1663,"g":0.0143,"v":0},{"e":"2027-06-17","t":"P","k":65,"oi":4990,"g":0.015,"v":3},{"e":"2027-06-17","t":"P","k":67.5,"oi":259,"g":0.0157,"v":0},{"e":"2027-06-17","t":"C","k":70,"oi":1495,"g":0.0147,"v":116},{"e":"2027-06-17","t":"P","k":70,"oi":2860,"g":0.0162,"v":5},{"e":"2027-06-17","t":"C","k":72.5,"oi":642,"g":0.0149,"v":22},{"e":"2027-06-17","t":"P","k":72.5,"oi":543,"g":0.0166,"v":0},{"e":"2027-06-17","t":"C","k":75,"oi":1701,"g":0.015,"v":4},{"e":"2027-06-17","t":"P","k":75,"oi":3000,"g":0.0169,"v":2},{"e":"2027-09-17","t":"P","k":60,"oi":306,"g":0.0118,"v":0},{"e":"2027-09-17","t":"P","k":67.5,"oi":511,"g":0.0137,"v":0},{"e":"2027-12-17","t":"C","k":60,"oi":368,"g":0.0098,"v":4},{"e":"2027-12-17","t":"P","k":60,"oi":3757,"g":0.0108,"v":0},{"e":"2027-12-17","t":"P","k":65,"oi":2271,"g":0.0121,"v":8},{"e":"2027-12-17","t":"P","k":67.5,"oi":202,"g":0.0126,"v":0},{"e":"2027-12-17","t":"C","k":70,"oi":414,"g":0.0114,"v":7},{"e":"2027-12-17","t":"P","k":70,"oi":2014,"g":0.0131,"v":0},{"e":"2027-12-17","t":"C","k":72.5,"oi":466,"g":0.0116,"v":0},{"e":"2027-12-17","t":"P","k":72.5,"oi":775,"g":0.0135,"v":8},{"e":"2027-12-17","t":"C","k":75,"oi":588,"g":0.0118,"v":1},{"e":"2027-12-17","t":"P","k":75,"oi":3357,"g":0.0139,"v":0},{"e":"2028-01-21","t":"C","k":60,"oi":1208,"g":0.0095,"v":8},{"e":"2028-01-21","t":"P","k":60,"oi":6695,"g":0.0105,"v":4},{"e":"2028-01-21","t":"P","k":62.5,"oi":947,"g":0.0111,"v":4},{"e":"2028-01-21","t":"C","k":65,"oi":524,"g":0.0104,"v":8},{"e":"2028-01-21","t":"P","k":65,"oi":5699,"g":0.0117,"v":4},{"e":"2028-01-21","t":"P","k":67.5,"oi":488,"g":0.0122,"v":0},{"e":"2028-01-21","t":"C","k":70,"oi":1337,"g":0.011,"v":13},{"e":"2028-01-21","t":"P","k":70,"oi":8231,"g":0.0127,"v":2},{"e":"2028-01-21","t":"C","k":72.5,"oi":699,"g":0.0112,"v":0},{"e":"2028-01-21","t":"P","k":72.5,"oi":1605,"g":0.0131,"v":1},{"e":"2028-01-21","t":"C","k":75,"oi":1755,"g":0.0114,"v":25},{"e":"2028-01-21","t":"P","k":75,"oi":6401,"g":0.0135,"v":0},{"e":"2028-06-16","t":"P","k":60,"oi":949,"g":0.0095,"v":1},{"e":"2028-06-16","t":"P","k":67.5,"oi":322,"g":0.011,"v":0},{"e":"2028-06-16","t":"C","k":75,"oi":267,"g":0.0101,"v":1},{"e":"2028-12-15","t":"P","k":60,"oi":666,"g":0.0085,"v":19},{"e":"2028-12-15","t":"P","k":62.5,"oi":1311,"g":0.009,"v":1},{"e":"2028-12-15","t":"P","k":65,"oi":645,"g":0.0094,"v":3},{"e":"2028-12-15","t":"C","k":70,"oi":734,"g":0.0083,"v":25},{"e":"2028-12-15","t":"P","k":70,"oi":1436,"g":0.0103,"v":1},{"e":"2028-12-15","t":"C","k":72.5,"oi":681,"g":0.0085,"v":11},{"e":"2028-12-15","t":"C","k":75,"oi":778,"g":0.0087,"v":28}]}